tcdr/__init__.py
tcdr/cli.py
tcdr/core.py
tcdr/responses.py
tcdr/settings.py
tcdr/features/__init__.py
tcdr/features/execute_tests.py
tcdr/features/generate_props.py
tcdr/features/scaffold_tcdr_app.py
tcdr/scaffold/tcdr_app/__init__.py
tcdr/scaffold/tcdr_app/main.py
tcdr/scaffold/tcdr_app/requirements.txt
tcdr/scaffold/tcdr_app/__pycache__/main.cpython-313.pyc
tcdr/scaffold/tcdr_app/__pycache__/main.cpython-314.pyc
tcdr/scaffold/tcdr_app/content/dashboard.json
tcdr/scaffold/tcdr_app/endpoints/__init__.py
tcdr/scaffold/tcdr_app/endpoints/__pycache__/__init__.cpython-313.pyc
tcdr/scaffold/tcdr_app/endpoints/__pycache__/__init__.cpython-314.pyc
tcdr/scaffold/tcdr_app/endpoints/api/__init__.py
tcdr/scaffold/tcdr_app/endpoints/api/tests.py
tcdr/scaffold/tcdr_app/endpoints/api/__pycache__/__init__.cpython-313.pyc
tcdr/scaffold/tcdr_app/endpoints/api/__pycache__/__init__.cpython-314.pyc
tcdr/scaffold/tcdr_app/endpoints/api/__pycache__/auth.cpython-313.pyc
tcdr/scaffold/tcdr_app/endpoints/api/__pycache__/dashboard.cpython-313.pyc
tcdr/scaffold/tcdr_app/endpoints/api/__pycache__/hello.cpython-313.pyc
tcdr/scaffold/tcdr_app/endpoints/api/__pycache__/tests.cpython-313.pyc
tcdr/scaffold/tcdr_app/endpoints/api/__pycache__/tests.cpython-314.pyc
tcdr/scaffold/tcdr_app/endpoints/views/__init__.py
tcdr/scaffold/tcdr_app/endpoints/views/dashboard.py
tcdr/scaffold/tcdr_app/endpoints/views/__pycache__/__init__.cpython-313.pyc
tcdr/scaffold/tcdr_app/endpoints/views/__pycache__/__init__.cpython-314.pyc
tcdr/scaffold/tcdr_app/endpoints/views/__pycache__/about.cpython-313.pyc
tcdr/scaffold/tcdr_app/endpoints/views/__pycache__/bhumika.cpython-313.pyc
tcdr/scaffold/tcdr_app/endpoints/views/__pycache__/dashboard.cpython-313.pyc
tcdr/scaffold/tcdr_app/endpoints/views/__pycache__/dashboard.cpython-314.pyc
tcdr/scaffold/tcdr_app/endpoints/views/__pycache__/hello.cpython-313.pyc
tcdr/scaffold/tcdr_app/endpoints/views/__pycache__/index.cpython-313.pyc
tcdr-0.0.1.dist-info/licenses/LICENSE
tcdr-0.0.1.dist-info/METADATA
tcdr-0.0.1.dist-info/WHEEL
tcdr-0.0.1.dist-info/entry_points.txt
tcdr-0.0.1.dist-info/top_level.txt
tcdr-0.0.1.dist-info/RECORD
