Metadata-Version: 2.4
Name: tcdr
Version: 0.0.1
Summary: thecode.report — zero-config .NET coverage dashboard powered by Z8ter
Author-email: Ashesh Nepal <nepalashesh8@gmail.com>
License: MIT License
Project-URL: Homepage, https://github.com/ashesh808/thecodedotreport
Project-URL: Issues, https://github.com/ashesh808/thecodedotreport/issues
Requires-Python: >=3.10
License-File: LICENSE
Requires-Dist: Jinja2==3.1.6
Requires-Dist: z8ter[auth]==0.2.6
Requires-Dist: uvicorn[standard]==0.35.0
Requires-Dist: platformdirs==4.3.8
Requires-Dist: watchdog==4.0.1
Dynamic: license-file
